rcca/__init__.py
pyrcca-0.1.dist-info/LICENSE
pyrcca-0.1.dist-info/METADATA
pyrcca-0.1.dist-info/WHEEL
pyrcca-0.1.dist-info/top_level.txt
pyrcca-0.1.dist-info/RECORD
