Metadata-Version: 2.1
Name: pyrcca
Version: 0.1
Summary: Regularized kernel canonical correlation analysis in Python.
Home-page: https://github.com/gallantlab/pyrcca
Author: Bilenko et al
License: Free for non-commercial use
Platform: UNKNOWN
Requires-Dist: h5py
Requires-Dist: numpy
Requires-Dist: scipy
